parseutil/__init__.py
parseutil/colors.py
parseutil/diff.py
parseutil/text.py
parseutil/time.py
parseutil/types.py
parseutil-0.2.0.dist-info/METADATA
parseutil-0.2.0.dist-info/WHEEL
parseutil-0.2.0.dist-info/RECORD
