Metadata-Version: 2.3
Name: parseutil
Version: 0.2.0
Summary: The missing text and time parsing toolkit for Python
Author: Danny Stewart
Author-email: danny@stewart.cc
Requires-Python: >=3.12
Classifier: Programming Language :: Python :: 3
Classifier: Programming Language :: Python :: 3.12
Classifier: Programming Language :: Python :: 3.13
Requires-Dist: devpkg (>=0.2.1)
Requires-Dist: logician (>=0.3.3)
Requires-Dist: python-dateutil (>=2.9.0.post0)
Requires-Dist: tzlocal (>=5.3.1)
